forward/__init__.py
forward/backend.py
forward/configuration.py
forward/experiment.py
forward/genotype.py
forward/tasks.py
forward/utils.py
forward/version.py
forward/phenotype/__init__.py
forward/phenotype/db.py
forward/phenotype/icd.py
forward/phenotype/variables.py
forward/scripts/__init__.py
forward/scripts/forward_cli.py
forward/static/bower.json
forward/static/bower_components/d3/.bower.json
forward/static/bower_components/d3/.gitattributes
forward/static/bower_components/d3/CONTRIBUTING.md
forward/static/bower_components/d3/LICENSE
forward/static/bower_components/d3/README.md
forward/static/bower_components/d3/bower.json
forward/static/bower_components/d3/d3.js
forward/static/bower_components/d3/d3.min.js
forward/static/bower_components/d3/package.js
forward/static/bower_components/jquery/.bower.json
forward/static/bower_components/jquery/MIT-LICENSE.txt
forward/static/bower_components/jquery/bower.json
forward/static/bower_components/jquery/dist/jquery.js
forward/static/bower_components/jquery/dist/jquery.min.js
forward/static/bower_components/jquery/dist/jquery.min.map
forward/static/bower_components/jquery/src/ajax.js
forward/static/bower_components/jquery/src/attributes.js
forward/static/bower_components/jquery/src/callbacks.js
forward/static/bower_components/jquery/src/core.js
forward/static/bower_components/jquery/src/css.js
forward/static/bower_components/jquery/src/data.js
forward/static/bower_components/jquery/src/deferred.js
forward/static/bower_components/jquery/src/deprecated.js
forward/static/bower_components/jquery/src/dimensions.js
forward/static/bower_components/jquery/src/effects.js
forward/static/bower_components/jquery/src/event.js
forward/static/bower_components/jquery/src/intro.js
forward/static/bower_components/jquery/src/jquery.js
forward/static/bower_components/jquery/src/manipulation.js
forward/static/bower_components/jquery/src/offset.js
forward-0.1.0.dist-info/DESCRIPTION.rst
forward-0.1.0.dist-info/METADATA
forward-0.1.0.dist-info/RECORD
forward-0.1.0.dist-info/WHEEL
forward-0.1.0.dist-info/entry_points.txt
forward-0.1.0.dist-info/metadata.json
forward-0.1.0.dist-info/pbr.json
forward-0.1.0.dist-info/top_level.txt
