Metadata-Version: 1.1
Name: forward
Version: 0.1.0
Summary: Tool for gene-based phenomic experiments using cohorts.
Home-page: https://github.com/legaultmarc/forward
Author: Marc-André Legault
Author-email: legaultmarc@gmail.com
License: CC BY-NC 4.0
Keywords: bioinformatics genomics phewas epidemiology cohort
Platform: UNKNOWN
Classifier: Development Status :: 4 - Beta
Classifier: Intended Audience :: Developers
Classifier: Intended Audience :: Science/Research
Classifier: Operating System :: Unix
Classifier: Operating System :: MacOS :: MacOS X
Classifier: Operating System :: POSIX :: Linux
Classifier: Programming Language :: Python
Classifier: Programming Language :: Python :: 2.7
Classifier: Programming Language :: Python :: 3
Classifier: Topic :: Scientific/Engineering :: Bio-Informatics
